ereach_douyin_mcp_server/__init__.py
ereach_douyin_mcp_server/__main__.py
ereach_douyin_mcp_server/cli.py
ereach_douyin_mcp_server/douyin_proxy.py
ereach_douyin_mcp_server/mcp_server.py
ereach_douyin_mcp_server/server.py
ereach_douyin_mcp_server/lib/cookies.py
ereach_douyin_mcp_server/lib/douyin.py
ereach_douyin_mcp_server/lib/download.py
ereach_douyin_mcp_server/lib/execjs_fix.py
ereach_douyin_mcp_server/lib/redis_cache.py
ereach_douyin_mcp_server/lib/request.py
ereach_douyin_mcp_server/lib/util.py
ereach_douyin_mcp_server/lib/js/douyin.js
ereach_douyin_mcp_server/static/ico.ico
ereach_douyin_mcp_server/static/image.png
ereach_douyin_mcp_server/test/test_douyin.py
ereach_douyin_mcp_server/test/test_request.py
ereach_douyin_mcp_server/test/test_utils.py
ereach_douyin_mcp_server/test/json/浏览器.json
ereach_douyin_mcp_server/test/json/请求 copy.json
ereach_douyin_mcp_server/test/json/请求.json
ereach_douyin_mcp_server-0.0.12.dist-info/METADATA
ereach_douyin_mcp_server-0.0.12.dist-info/WHEEL
ereach_douyin_mcp_server-0.0.12.dist-info/entry_points.txt
ereach_douyin_mcp_server-0.0.12.dist-info/licenses/LICENSE
ereach_douyin_mcp_server-0.0.12.dist-info/RECORD
