Metadata-Version: 2.4
Name: ereach-douyin-mcp-server
Version: 0.0.12
Summary: MCP server for downloading Douyin videos and extracting text
Project-URL: Homepage, https://github.com/zhuxin2019/douyin-mcp-server.git
Project-URL: Repository, https://github.com/zhuxin2019/douyin-mcp-server.git
Project-URL: Issues, https://github.com/zhuxin2019/douyin-mcp-server.git/issues
Author-email: "xin.zhu" <tony.zhu.cn@qq.com>
License: MIT
License-File: LICENSE
Classifier: Development Status :: 3 - Alpha
Classifier: Intended Audience :: Developers
Classifier: License :: OSI Approved :: MIT License
Classifier: Programming Language :: Python :: 3
Classifier: Programming Language :: Python :: 3.8
Classifier: Programming Language :: Python :: 3.9
Classifier: Programming Language :: Python :: 3.10
Classifier: Programming Language :: Python :: 3.11
Classifier: Programming Language :: Python :: 3.12
Requires-Python: >=3.8
Requires-Dist: click
Requires-Dist: dbutils
Requires-Dist: dotenv
Requires-Dist: fastmcp
Requires-Dist: ffmpeg-python
Requires-Dist: flask
Requires-Dist: flask-cors
Requires-Dist: flask-jwt-extended
Requires-Dist: httpx[socks]
Requires-Dist: loguru
Requires-Dist: mcp>=1.0.0
Requires-Dist: pyexecjs
Requires-Dist: pymysql
Requires-Dist: redis
Requires-Dist: requests
Requires-Dist: rookiepy
Requires-Dist: tqdm
Requires-Dist: ujson
